README.md
setup.py
aqua/__init__.py
aqua/aqua.py
aqua.egg-info/PKG-INFO
aqua.egg-info/SOURCES.txt
aqua.egg-info/dependency_links.txt
aqua.egg-info/not-zip-safe
aqua.egg-info/requires.txt
aqua.egg-info/top_level.txt