Metadata-Version: 1.0
Name: aqua
Version: 0.1b0
Summary: Python 3 client for Aqua's CSP Platform
Home-page: https://github.com/
Author: Jeff Thorne
Author-email: jthorne@u.washington.edu
License: MIT
Platform: UNKNOWN
